xontrib/pm.py
xontrib_pm-0.3.4.dist-info/licenses/LICENSE
xontrib_pm-0.3.4.dist-info/METADATA
xontrib_pm-0.3.4.dist-info/WHEEL
xontrib_pm-0.3.4.dist-info/top_level.txt
xontrib_pm-0.3.4.dist-info/RECORD
