Metadata-Version: 2.4
Name: xontrib-pm
Version: 0.3.4
Summary: Copy output to clipboard.
Author-email: anki-code <no@no.no>
License: MIT License
Project-URL: Homepage, https://github.com/anki-code/xontrib-pm
Project-URL: Documentation, https://github.com/anki-code/xontrib-pm/blob/master/README.md
Project-URL: Code, https://github.com/anki-code/xontrib-pm
Project-URL: Issue tracker, https://github.com/anki-code/xontrib-pm/issues
Platform: any
Classifier: Programming Language :: Python :: 3
Classifier: License :: OSI Approved :: MIT License
Classifier: Operating System :: OS Independent
Classifier: Topic :: System :: Shells
Classifier: Topic :: System :: System Shells
Classifier: Topic :: Terminals
Requires-Python: >=3.8
License-File: LICENSE
Requires-Dist: xonsh>=0.12.5
Provides-Extra: dev
Requires-Dist: pytest>=7.0; extra == "dev"
Dynamic: license-file
